matbench/__init__.py
matbench/bench.py
matbench/constants.py
matbench/data_ops.py
matbench/matbench_v0.1_dataset_metadata.json
matbench/matbench_v0.1_validation.json
matbench/metadata.py
matbench/task.py
matbench/util.py
matbench/tests/__init__.py
matbench/tests/mb_3_tasks_random.json
matbench/tests/mb_all_tasks_random.json
matbench/tests/msonability_matbench_dielectric.json
matbench/tests/msonability_matbench_glass.json
matbench/tests/msonability_matbench_steels.json
matbench/tests/scores_matbench_dielectric_perfect.json
matbench/tests/scores_matbench_glass_perfect.json
matbench/tests/test_bench.py
matbench/tests/test_data_ops.py
matbench/tests/test_metadata.py
matbench/tests/test_task.py
matbench/tests/test_util.py
matbench/tests/util.py
scripts/__init__.py
scripts/coverage.py
scripts/mbv01_get_ds_stats.py
scripts/mvb01_generate_validation.py
scripts/read_json_to_html.py
scripts/rebuild_docs.py
scripts/release.py
scripts/test_submission.py
matbench-0.6.dist-info/LICENSE
matbench-0.6.dist-info/METADATA
matbench-0.6.dist-info/WHEEL
matbench-0.6.dist-info/top_level.txt
matbench-0.6.dist-info/RECORD
