Metadata-Version: 2.1
Name: matbench
Version: 0.6
Summary: a machine learning benchmark for materials science
Home-page: https://github.com/materialsproject/matbench
Author: ['Alex Dunn', 'Anubhav Jain']
Author-email: ardunn@lbl.gov
License: modified BSD
Platform: UNKNOWN
License-File: LICENSE
Requires-Dist: matminer (==0.7.4)
Requires-Dist: scipy (==1.7.3)
Requires-Dist: monty (==2022.4.26)
Requires-Dist: scikit-learn (==1.0.1)
